Workbook

Sheet Cover & Assumptions
B2: RACELOGIC LIMITED - LBO MODEL
B3: Foresight Growth & Buyout pitch (UK & Ireland, £2-40m, sector-agnostic, equity release named) · Anchored on CH FY24 + BBG + Alpha Spread (May 2026)
B4: Prepared by A. Kumbhar · For discussion only · NOT a deal indication
B6: • FUND VEHICLE: Foresight Growth & Buyout (UK & Ireland mandate, £2m-£40m cheque, sector-agnostic, all transaction types incl. equity release). Refeyn (scientific instrumentation) is direct portfolio precedent.
B7: • ENTRY MULTIPLE BASIS: 8.0x ADJUSTED EBITDA. PE-comp standard. BBG reported 27.8x is on depressed GAAP basis (penalises serial-acquirer ABDP); adjusted basis at May-26 is ~8x.
B8: • CATALYST FRAMING: SUGGESTIVE not active. Cap-table grooming observable, but NO banker mandate and VBOX PRO launched Feb-26 contradicts harvest reading. Cold thematic pitch.
B9: • Warm intro to Julian Thomas confirmed NOT POSSIBLE - framing must reflect cold thematic approach
B11: SOURCING LEGEND
B12: VERIFIED | C12: CH FY24 (CRN 02743719), Bloomberg L.P. 23-May-2026, or Alpha Spread May-2026
B13: CALCULABLE | C13: Arithmetic from verified inputs
B14: ASSUMPTION | C14: Modelling choice - illustrative
B15: SUGGESTIVE | C15: Observable signal consistent with thesis, not confirmed by primary source
B17: COMP TABLE - May 2026; CLARIFIED MULTIPLE BASIS
B18: Comp | C18: Share Px | D18: Mkt Cap | E18: EV | F18: EV/EBITDA (BASIS)
B19: AB Dynamics (ABDP LN) GBP | C19: 1,128p | D19: £258.9m | E19: ~£228m est | F19: ~8x ADJUSTED EBITDA - PE-comp basis (BBG GAAP 27.8x penalises acquirer)
B20: HORIBA (6856 JP) JPY | C20: ¥25,875 | D20: ¥1,093B | E20: ¥1,003B | F20: 9.7x T12M EBITDA - large diversified comp
B21: Hexagon (HEXAB SS) SEK | C21: SEK 87.04 | D21: SEK 235.5bn | E21: n/a | F21: P/E 10.8x (EV/EBITDA not in BBG panel)
B22: Spectris (SXS LN) | C22: TAKEN PRIVATE | D22: by MI Metron | E22: 2025 | F22: Deal multiple UNVERIFIED
B24: Sources: Bloomberg L.P. 23-May-2026 (ABDP, HORIBA, HEXAB, SXS); Alpha Spread May-2026 (ABDP price)
B25: KEY READ: Racelogic entry 8.0x = parity with ABDP adjusted basis. No control premium.
B27: ENTRY ANCHORS - Companies House FY24 + Bloomberg
B29: FY24 Revenue (£m) | C29: 22.684 | E29: VERIFIED | F29: CH consolidated income statement - turnover £22,683,967
B30: FY24 EBITDA (£m) | C30: 3.467 | E30: VERIFIED | F30: CH Note 6 - OP £3.084m + D £0.359m + amort £0.025m
B31: FY24 EBITDA margin | C31: =C30/C29 -> 0.15283901 | E31: CALCULABLE | F31: 15.3% - cyclical trough
B32: 9-yr mean EBITDA margin (BBG) | C32: 0.227 | E32: VERIFIED | F32: BBG FY16-FY24 simple mean - context for 21% Y5 target
B33: FY24 D&A (£m) | C33: 0.384 | E33: VERIFIED
B34: LT debt (£m) | C34: 0 | E34: VERIFIED | F34: CH balance sheet - no LT borrowings; BBG 9-yr confirms
B35: Cash (£m) | C35: 3.237 | E35: VERIFIED
B36: Net debt / (net cash) (£m) | C36: =C34-C35 -> -3.237 | E36: CALCULABLE
B38: CATALYST SIGNALS - SUGGESTIVE NOT ACTIVE
B39: Founder age | C39: 57 | E39: VERIFIED
B40: SH03 buybacks FY21-FY26 | C40: 9 | E40: SUGGESTIVE | F40: Pattern observable; intent UNCONFIRMED
B41: External CEO (MacKie) | C41: Active | E41: SUGGESTIVE | F41: FY24 accounts signed by Mackie. Reading = transition prep, not confirmed
B42: Mar-26 board cleanup | C42: Yes | E42: SUGGESTIVE | F42: 3 officers terminated 03-Mar-26 + SH03 02-Mar
B43: Banker mandate | C43: None visible | E43: VERIFIED | F43: No RNS, no public M&A news, no Tracxn/Crunchbase deal record
B44: VBOX PRO launch Feb-2026 | C44: Yes | E44: SUGGESTIVE | F44: Fresh product launch CONTRADICTS sale-grooming reading - argues for continued investment
B45: Net catalyst read | E45: SUGGESTIVE
B47: TRANSACTION ASSUMPTIONS - ILLUSTRATIVE
B49: Entry EV/EBITDA (x, ADJUSTED basis) | C49: 8 | E49: ASSUMPTION
B50: Implied Entry EV (£m) | C50: =C30*C49 -> 27.736 | E50: CALCULABLE
B51: Implied 100% equity value (£m) | C51: =C50-C36 -> 30.973 | E51: CALCULABLE
B52: Transaction fees (£m) | C52: 0.85 | E52: ASSUMPTION
B53: Entry leverage (x EBITDA) | C53: 3 | E53: ASSUMPTION
B54: New senior debt (£m) | C54: =ROUND(C30*C53,2) -> 10.4 | E54: CALCULABLE
B55: Founder rollover (£m) | C55: 14 | E55: ASSUMPTION | F55: ~64% retained - equity release in substance
B56: Foresight G&B sponsor equity (£m) - PLUG | C56: =C51+C52-C54-C55 -> 7.423 | E56: CALCULABLE | F56: Sits inside £2-40m Foresight G&B band
B57: Foresight stake post-deal | C57: =C56/(C56+C55) -> 0.34649676 | E57: CALCULABLE
B59: OPERATING ASSUMPTIONS
B61: Revenue growth p.a. | C61: 0.05 | E61: ASSUMPTION | F61: 9-yr CAGR was 8.2%; base case below
B62: EBITDA margin - entry | C62: =C31 -> 0.15283901 | E62: CALCULABLE
B63: EBITDA margin - Y5 target | C63: 0.21 | E63: ASSUMPTION | F63: Below 9-yr mean 22.7%. Biggest swing factor.
B64: D&A % of revenue | C64: =C33/C29 -> 0.016928231 | E64: CALCULABLE
B65: Capex % of revenue | C65: 0.029 | E65: VERIFIED | F65: CH cash flow
B66: WC % of revenue change | C66: 0.4 | E66: ASSUMPTION
B67: Cash tax rate | C67: 0.12 | E67: VERIFIED | F67: BBG 9-yr avg ~10%; R&D enhanced deduction per CH Note 7
B68: Senior debt rate | C68: 0.085 | E68: ASSUMPTION
B69: Cash sweep | C69: 1 | E69: ASSUMPTION
B70: Min cash (£m) | C70: 2 | E70: ASSUMPTION
B72: EXIT ASSUMPTIONS
B73: Hold period (years) | C73: 5 | E73: ASSUMPTION
B74: Exit EV/EBITDA (x) | C74: 9.5 | E74: ASSUMPTION

Sheet Model
B1: RACELOGIC LIMITED - LBO MODEL
B3: ENTRY VALUATION BUILD - how the equity price is derived
B4: LTM EBITDA (£m) | C4: ='Cover & Assumptions'!$C$30 -> 3.467 | E4: VERIFIED | F4: CH FY24 (Note 6): OpProfit £3.084m + D £0.359m + amort £0.025m
B5: Entry EV / LTM EBITDA multiple (x) | C5: ='Cover & Assumptions'!$C$49 -> 8 | E5: ASSUMPTION | F5: 8.0x = ABDP current adjusted EBITDA basis (no control premium, equity release)
B6: Implied Entry Enterprise Value (£m) | C6: =C4*C5 -> 27.736 | E6: CALCULABLE | F6: LTM EBITDA × entry multiple
B7: less: Long-term debt (£m) | C7: ='Cover & Assumptions'!$C$34 -> 0 | E7: VERIFIED | F7: CH balance sheet - no LT borrowings
B8: plus: Cash (£m) | C8: ='Cover & Assumptions'!$C$35 -> 3.237 | E8: VERIFIED | F8: CH balance sheet
B9: Equity value at entry - 100% basis (£m) | C9: =C6-C7+C8 -> 30.973 | E9: CALCULABLE | F9: Entry EV − LT debt + cash = price paid to existing shareholders for 100% of equity
B11: SOURCES & USES - illustrative entry structure
B12: USES OF FUNDS (£m) | F12: SOURCES OF FUNDS (£m)
B13: Acquire 100% equity (at Entry EV − net debt) | C13: =C9 -> 30.973 | F13: Acquisition debt | G13: ='Cover & Assumptions'!$C$54 -> 10.4
B14: Transaction fees | C14: ='Cover & Assumptions'!$C$52 -> 0.85 | F14: Founder rollover (Thomas) | G14: ='Cover & Assumptions'!$C$55 -> 14
F15: Foresight G&B sponsor equity | G15: =C16-G13-G14 -> 7.423
B16: TOTAL USES | C16: =SUM(C13:C15) -> 31.823 | F16: TOTAL SOURCES | G16: =SUM(G13:G15) -> 31.823
F17: Foresight equity % | G17: =G15/(G15+G14) -> 0.34649676
E18: Check: Sources = Uses | G18: =IF(ROUND(G16-C16,2)=0,"OK","ERROR") -> OK
B19: Sponsor equity is the plug. Sponsor cheque fits Foresight Growth & Buyout £0.5-15m active mandate (press 2025).
B21: OPERATING MODEL - 5-year projection
B22: £m | C22: FY24A (Entry) | D22: Year 1 | E22: Year 2 | F22: Year 3 | G22: Year 4 | H22: Year 5
B23: Revenue | C23: ='Cover & Assumptions'!$C$29 -> 22.684 | D23: =C23*(1+'Cover & Assumptions'!$C$61) -> 23.8182 | E23: =D23*(1+'Cover & Assumptions'!$C$61) -> 25.00911 | F23: =E23*(1+'Cover & Assumptions'!$C$61) -> 26.259566 | G23: =F23*(1+'Cover & Assumptions'!$C$61) -> 27.572544 | H23: =G23*(1+'Cover & Assumptions'!$C$61) -> 28.951171
B24: EBITDA margin | C24: ='Cover & Assumptions'!$C$62 -> 0.15283901 | D24: ='Cover & Assumptions'!$C$62+('Cover & Assumptions'!$C$63-'Cover & Assumptions'!$C$62)*1/5 -> 0.1642712 | E24: ='Cover & Assumptions'!$C$62+('Cover & Assumptions'!$C$63-'Cover & Assumptions'!$C$62)*2/5 -> 0.1757034 | F24: ='Cover & Assumptions'!$C$62+('Cover & Assumptions'!$C$63-'Cover & Assumptions'!$C$62)*3/5 -> 0.1871356 | G24: ='Cover & Assumptions'!$C$62+('Cover & Assumptions'!$C$63-'Cover & Assumptions'!$C$62)*4/5 -> 0.1985678 | H24: ='Cover & Assumptions'!$C$62+('Cover & Assumptions'!$C$63-'Cover & Assumptions'!$C$62)*5/5 -> 0.21
B25: EBITDA | C25: =C23*C24 -> 3.467 | D25: =D23*D24 -> 3.9126444 | E25: =E23*E24 -> 4.3941857 | F25: =F23*F24 -> 4.9140996 | G25: =G23*G24 -> 5.4750194 | H25: =H23*H24 -> 6.0797459
B26: D&A | C26: =-C23*'Cover & Assumptions'!$C$64 -> -0.384 | D26: =-D23*'Cover & Assumptions'!$C$64 -> -0.4032 | E26: =-E23*'Cover & Assumptions'!$C$64 -> -0.42336 | F26: =-F23*'Cover & Assumptions'!$C$64 -> -0.444528 | G26: =-G23*'Cover & Assumptions'!$C$64 -> -0.4667544 | H26: =-H23*'Cover & Assumptions'!$C$64 -> -0.49009212
B27: EBIT | C27: =C25+C26 -> 3.083 | D27: =D25+D26 -> 3.5094444 | E27: =E25+E26 -> 3.9708257 | F27: =F25+F26 -> 4.4695716 | G27: =G25+G26 -> 5.008265 | H27: =H25+H26 -> 5.5896538
B28: Cash interest (senior) | C28: 0 | D28: =-D45 -> -0.884 | E28: =-E45 -> -0.75061942 | F28: =-F45 -> -0.57590079 | G28: =-G45 -> -0.35411464 | H28: =-H45 -> -0.078917656
B29: Profit before tax | C29: =C27+C28 -> 3.083 | D29: =D27+D28 -> 2.6254444 | E29: =E27+E28 -> 3.2202063 | F29: =F27+F28 -> 3.8936708 | G29: =G27+G28 -> 4.6541503 | H29: =H27+H28 -> 5.5107361
B30: Cash tax (12% effective) | C30: =-MAX(0,C29)*'Cover & Assumptions'!$C$67 -> -0.36996 | D30: =-MAX(0,D29)*'Cover & Assumptions'!$C$67 -> -0.31505333 | E30: =-MAX(0,E29)*'Cover & Assumptions'!$C$67 -> -0.38642476 | F30: =-MAX(0,F29)*'Cover & Assumptions'!$C$67 -> -0.4672405 | G30: =-MAX(0,G29)*'Cover & Assumptions'!$C$67 -> -0.55849804 | H30: =-MAX(0,H29)*'Cover & Assumptions'!$C$67 -> -0.66128834
B31: Net profit | C31: =C29+C30 -> 2.71304 | D31: =D29+D30 -> 2.3103911 | E31: =E29+E30 -> 2.8337816 | F31: =F29+F30 -> 3.4264303 | G31: =G29+G30 -> 4.0956523 | H31: =H29+H30 -> 4.8494478
B33: FREE CASH FLOW BUILD
B34: EBITDA | C34: =C25 -> 3.467 | D34: =D25 -> 3.9126444 | E34: =E25 -> 4.3941857 | F34: =F25 -> 4.9140996 | G34: =G25 -> 5.4750194 | H34: =H25 -> 6.0797459
B35: Less: capex | C35: =-C23*'Cover & Assumptions'!$C$65 -> -0.657836 | D35: =-D23*'Cover & Assumptions'!$C$65 -> -0.6907278 | E35: =-E23*'Cover & Assumptions'!$C$65 -> -0.72526419 | F35: =-F23*'Cover & Assumptions'!$C$65 -> -0.7615274 | G35: =-G23*'Cover & Assumptions'!$C$65 -> -0.79960377 | H35: =-H23*'Cover & Assumptions'!$C$65 -> -0.83958396
B36: Less: WC change | C36: 0 | D36: =-(D23-C23)*'Cover & Assumptions'!$C$66 -> -0.45368 | E36: =-(E23-D23)*'Cover & Assumptions'!$C$66 -> -0.476364 | F36: =-(F23-E23)*'Cover & Assumptions'!$C$66 -> -0.5001822 | G36: =-(G23-F23)*'Cover & Assumptions'!$C$66 -> -0.52519131 | H36: =-(H23-G23)*'Cover & Assumptions'!$C$66 -> -0.55145088
B37: Less: cash interest | C37: =C28 -> 0 | D37: =D28 -> -0.884 | E37: =E28 -> -0.75061942 | F37: =F28 -> -0.57590079 | G37: =G28 -> -0.35411464 | H37: =H28 -> -0.078917656
B38: Less: cash tax | C38: =C30 -> -0.36996 | D38: =D30 -> -0.31505333 | E38: =E30 -> -0.38642476 | F38: =F30 -> -0.4672405 | G38: =G30 -> -0.55849804 | H38: =H30 -> -0.66128834
B39: FCF (pre-debt repayment) | C39: =C34+C35+C36+C37+C38 -> 2.439204 | D39: =D34+D35+D36+D37+D38 -> 1.5691833 | E39: =E34+E35+E36+E37+E38 -> 2.0555134 | F39: =F34+F35+F36+F37+F38 -> 2.6092487 | G39: =G34+G35+G36+G37+G38 -> 3.2376116 | H39: =H34+H35+H36+H37+H38 -> 3.9485051
B41: ACQUISITION DEBT SCHEDULE & CASH SWEEP
B42: £m | C42: FY24A (Entry) | D42: Year 1 | E42: Year 2 | F42: Year 3 | G42: Year 4 | H42: Year 5
B43: Opening debt | C43: ='Cover & Assumptions'!$C$54 -> 10.4 | D43: =C43 -> 10.4 | E43: =D46 -> 8.8308167 | F43: =E46 -> 6.7753034 | G43: =F46 -> 4.1660546 | H43: =G46 -> 0.92844302
B44: Interest rate | C44: ='Cover & Assumptions'!$C$68 -> 0.085 | D44: ='Cover & Assumptions'!$C$68 -> 0.085 | E44: ='Cover & Assumptions'!$C$68 -> 0.085 | F44: ='Cover & Assumptions'!$C$68 -> 0.085 | G44: ='Cover & Assumptions'!$C$68 -> 0.085 | H44: ='Cover & Assumptions'!$C$68 -> 0.085
B45: Cash interest | C45: 0 | D45: =D43*D44 -> 0.884 | E45: =E43*E44 -> 0.75061942 | F45: =F43*F44 -> 0.57590079 | G45: =G43*G44 -> 0.35411464 | H45: =H43*H44 -> 0.078917656
B46: Closing debt | C46: ='Cover & Assumptions'!$C$54 -> 10.4 | D46: =MAX(0,D43-D47) -> 8.8308167 | E46: =MAX(0,E43-E47) -> 6.7753034 | F46: =MAX(0,F43-F47) -> 4.1660546 | G46: =MAX(0,G43-G47) -> 0.92844302 | H46: =MAX(0,H43-H47) -> 0
B47: Cash sweep | C47: 0 | D47: =MIN(D43,MAX(0,D39)*'Cover & Assumptions'!$C$69) -> 1.5691833 | E47: =MIN(E43,MAX(0,E39)*'Cover & Assumptions'!$C$69) -> 2.0555134 | F47: =MIN(F43,MAX(0,F39)*'Cover & Assumptions'!$C$69) -> 2.6092487 | G47: =MIN(G43,MAX(0,G39)*'Cover & Assumptions'!$C$69) -> 3.2376116 | H47: =MIN(H43,MAX(0,H39)*'Cover & Assumptions'!$C$69) -> 0.92844302
B49: Net senior debt at exit (£m) | C49: =H46-'Cover & Assumptions'!$C$70 -> -2
B51: RETURNS - equity bridge
B52: EXIT (YEAR 5)
B53: Y5 EBITDA | C53: =H25 -> 6.0797459
B54: Exit EV/EBITDA | C54: ='Cover & Assumptions'!$C$74 -> 9.5
B55: Exit EV | C55: =C53*C54 -> 57.757586
B56: Less: net senior debt | C56: =-C49 -> 2
B57: Exit equity value (total) | C57: =C55+C56 -> 59.757586
B59: RETURNS TO FORESIGHT G&B
B60: Sponsor equity invested | C60: =G15 -> 7.423
B61: Foresight stake | C61: =G17 -> 0.34649676
B62: Foresight share of exit | C62: =C57*C61 -> 20.70581
B63: MOIC | C63: =C62/C60 -> 2.7894126
B64: Hold period (years) | C64: ='Cover & Assumptions'!$C$73 -> 5
B65: IRR | C65: =(C63)^(1/C64)-1 -> 0.22772911
B67: SENSITIVITY
B68: Base sponsor equity | C68: =C60 -> 7.423
B69: Base Y5 EBITDA | C69: =H25 -> 6.0797459
B70: Base Y5 net debt | C70: =C49 -> -2
B71: Foresight stake | C71: =G17 -> 0.34649676
B73: TABLE 1 - Foresight MOIC: Exit multiple (rows) × Y5 EBITDA margin (cols)
B74: Exit x \ Margin | C74: 0.17 | D74: 0.19 | E74: 0.21 | F74: 0.23 | G74: 0.25
B75: 7 | C75: =((H23*0.17)*$B75-$C$70)*$C$71/$C$68 -> 1.7015308 | D75: =((H23*0.19)*$B75-$C$70)*$C$71/$C$68 -> 1.8907276 | E75: =((H23*0.21)*$B75-$C$70)*$C$71/$C$68 -> 2.0799244 | F75: =((H23*0.23)*$B75-$C$70)*$C$71/$C$68 -> 2.2691213 | G75: =((H23*0.25)*$B75-$C$70)*$C$71/$C$68 -> 2.4583181
B76: 8.5 | C76: =((H23*0.17)*$B76-$C$70)*$C$71/$C$68 -> 2.0461393 | D76: =((H23*0.19)*$B76-$C$70)*$C$71/$C$68 -> 2.2758783 | E76: =((H23*0.21)*$B76-$C$70)*$C$71/$C$68 -> 2.5056173 | F76: =((H23*0.23)*$B76-$C$70)*$C$71/$C$68 -> 2.7353564 | G76: =((H23*0.25)*$B76-$C$70)*$C$71/$C$68 -> 2.9650954
B77: 9.5 | C77: =((H23*0.17)*$B77-$C$70)*$C$71/$C$68 -> 2.2758783 | D77: =((H23*0.19)*$B77-$C$70)*$C$71/$C$68 -> 2.5326455 | E77: =((H23*0.21)*$B77-$C$70)*$C$71/$C$68 -> 2.7894126 | F77: =((H23*0.23)*$B77-$C$70)*$C$71/$C$68 -> 3.0461797 | G77: =((H23*0.25)*$B77-$C$70)*$C$71/$C$68 -> 3.3029469
B78: 10.5 | C78: =((H23*0.17)*$B78-$C$70)*$C$71/$C$68 -> 2.5056173 | D78: =((H23*0.19)*$B78-$C$70)*$C$71/$C$68 -> 2.7894126 | E78: =((H23*0.21)*$B78-$C$70)*$C$71/$C$68 -> 3.0732079 | F78: =((H23*0.23)*$B78-$C$70)*$C$71/$C$68 -> 3.3570031 | G78: =((H23*0.25)*$B78-$C$70)*$C$71/$C$68 -> 3.6407984
B79: 12 | C79: =((H23*0.17)*$B79-$C$70)*$C$71/$C$68 -> 2.8502259 | D79: =((H23*0.19)*$B79-$C$70)*$C$71/$C$68 -> 3.1745633 | E79: =((H23*0.21)*$B79-$C$70)*$C$71/$C$68 -> 3.4989008 | F79: =((H23*0.23)*$B79-$C$70)*$C$71/$C$68 -> 3.8232382 | G79: =((H23*0.25)*$B79-$C$70)*$C$71/$C$68 -> 4.1475756
B81: TABLE 2 - Foresight IRR: Revenue growth × Exit multiple (margin held at 21%)
B82: Growth \ Exit x | C82: 7 | D82: 8.5 | E82: 9.5 | F82: 10.5 | G82: 12
B83: 0.02 | C83: =(((('Cover & Assumptions'!$C$29*(1+$B83)^5)*'Cover & Assumptions'!$C$63*7-$C$70)*$C$71/$C$68)^(1/5))-1 -> 0.12622803 | D83: =(((('Cover & Assumptions'!$C$29*(1+$B83)^5)*'Cover & Assumptions'!$C$63*8.5-$C$70)*$C$71/$C$68)^(1/5))-1 -> 0.16868406 | E83: =(((('Cover & Assumptions'!$C$29*(1+$B83)^5)*'Cover & Assumptions'!$C$63*9.5-$C$70)*$C$71/$C$68)^(1/5))-1 -> 0.19389367 | F83: =(((('Cover & Assumptions'!$C$29*(1+$B83)^5)*'Cover & Assumptions'!$C$63*10.5-$C$70)*$C$71/$C$68)^(1/5))-1 -> 0.217138 | G83: =(((('Cover & Assumptions'!$C$29*(1+$B83)^5)*'Cover & Assumptions'!$C$63*12-$C$70)*$C$71/$C$68)^(1/5))-1 -> 0.24898698
B84: 0.035 | C84: =(((('Cover & Assumptions'!$C$29*(1+$B84)^5)*'Cover & Assumptions'!$C$63*7-$C$70)*$C$71/$C$68)^(1/5))-1 -> 0.14196001 | D84: =(((('Cover & Assumptions'!$C$29*(1+$B84)^5)*'Cover & Assumptions'!$C$63*8.5-$C$70)*$C$71/$C$68)^(1/5))-1 -> 0.18515479 | E84: =(((('Cover & Assumptions'!$C$29*(1+$B84)^5)*'Cover & Assumptions'!$C$63*9.5-$C$70)*$C$71/$C$68)^(1/5))-1 -> 0.21079378 | F84: =(((('Cover & Assumptions'!$C$29*(1+$B84)^5)*'Cover & Assumptions'!$C$63*10.5-$C$70)*$C$71/$C$68)^(1/5))-1 -> 0.23442879 | G84: =(((('Cover & Assumptions'!$C$29*(1+$B84)^5)*'Cover & Assumptions'!$C$63*12-$C$70)*$C$71/$C$68)^(1/5))-1 -> 0.26680591
B85: 0.05 | C85: =(((('Cover & Assumptions'!$C$29*(1+$B85)^5)*'Cover & Assumptions'!$C$63*7-$C$70)*$C$71/$C$68)^(1/5))-1 -> 0.15773593 | D85: =(((('Cover & Assumptions'!$C$29*(1+$B85)^5)*'Cover & Assumptions'!$C$63*8.5-$C$70)*$C$71/$C$68)^(1/5))-1 -> 0.20166372 | E85: =(((('Cover & Assumptions'!$C$29*(1+$B85)^5)*'Cover & Assumptions'!$C$63*9.5-$C$70)*$C$71/$C$68)^(1/5))-1 -> 0.22772911 | F85: =(((('Cover & Assumptions'!$C$29*(1+$B85)^5)*'Cover & Assumptions'!$C$63*10.5-$C$70)*$C$71/$C$68)^(1/5))-1 -> 0.25175227 | G85: =(((('Cover & Assumptions'!$C$29*(1+$B85)^5)*'Cover & Assumptions'!$C$63*12-$C$70)*$C$71/$C$68)^(1/5))-1 -> 0.28465445
B86: 0.065 | C86: =(((('Cover & Assumptions'!$C$29*(1+$B86)^5)*'Cover & Assumptions'!$C$63*7-$C$70)*$C$71/$C$68)^(1/5))-1 -> 0.17355239 | D86: =(((('Cover & Assumptions'!$C$29*(1+$B86)^5)*'Cover & Assumptions'!$C$63*8.5-$C$70)*$C$71/$C$68)^(1/5))-1 -> 0.21820786 | E86: =(((('Cover & Assumptions'!$C$29*(1+$B86)^5)*'Cover & Assumptions'!$C$63*9.5-$C$70)*$C$71/$C$68)^(1/5))-1 -> 0.24469687 | F86: =(((('Cover & Assumptions'!$C$29*(1+$B86)^5)*'Cover & Assumptions'!$C$63*10.5-$C$70)*$C$71/$C$68)^(1/5))-1 -> 0.26910587 | G86: =(((('Cover & Assumptions'!$C$29*(1+$B86)^5)*'Cover & Assumptions'!$C$63*12-$C$70)*$C$71/$C$68)^(1/5))-1 -> 0.30253023
B87: 0.08 | C87: =(((('Cover & Assumptions'!$C$29*(1+$B87)^5)*'Cover & Assumptions'!$C$63*7-$C$70)*$C$71/$C$68)^(1/5))-1 -> 0.18940628 | D87: =(((('Cover & Assumptions'!$C$29*(1+$B87)^5)*'Cover & Assumptions'!$C$63*8.5-$C$70)*$C$71/$C$68)^(1/5))-1 -> 0.23478448 | E87: =(((('Cover & Assumptions'!$C$29*(1+$B87)^5)*'Cover & Assumptions'!$C$63*9.5-$C$70)*$C$71/$C$68)^(1/5))-1 -> 0.26169455 | F87: =(((('Cover & Assumptions'!$C$29*(1+$B87)^5)*'Cover & Assumptions'!$C$63*10.5-$C$70)*$C$71/$C$68)^(1/5))-1 -> 0.28648723 | G87: =(((('Cover & Assumptions'!$C$29*(1+$B87)^5)*'Cover & Assumptions'!$C$63*12-$C$70)*$C$71/$C$68)^(1/5))-1 -> 0.32043113
B89: SCENARIO SUMMARY
B90: Bear: Y5 margin 19%, exit 7.0x
B91: Base: Y5 margin 21%, exit 9.5x - HORIBA-current, partial recovery
B92: Bull: Y5 margin 23%, exit 12.0x - full sector re-rating
