Workbook

Sheet Cover & Assumptions
B2: TYRE SPOT LIMITED — LBO MODEL
B3: Illustrative founder-succession buyout · Anchored on Companies House FY25 audited accounts (CRN 02854187)
B4: Prepared by A. Kumbhar · For discussion only · NOT a deal indication
B6: ASSUMPTIONS & KEY CAVEATS
B7: • Screening model. Entry anchors sourced from Companies House Tyre Spot Limited FY March 2025 audited accounts.
B8: • Every input is colour-coded and tagged.
B9: • VERIFIED (green) = traced to Companies House Tyre Spot Limited FY March 2025 filing (CRN 02854187).
B10: • CALCULABLE (blue) = derived by formula from verified inputs.
B11: • ASSUMPTION (amber) = modelling choice; returns rest on these.
B12: • FLAGGED (purple) = not yet fully sourced; confirm before relying on it.
B13: • Biggest swing factor: admin discipline execution. £5.5m → £8.3m admin growth FY22-FY25 is the load-bearing assumption to reverse.
B15: SOURCING LEGEND
B16: VERIFIED | C16: Companies House Tyre Spot Limited FY March 2025, CRN 02854187
B17: CALCULABLE | C17: Arithmetic from verified inputs
B18: ASSUMPTION | C18: Modelling choice — illustrative, not a fact or deal indication
B19: FLAGGED | C19: Not yet fully sourced — confirm before relying on it
B20: Colour: blue = input you can change · black = formula · green = link from this workbook · grey = source note
B22: TYRE SPOT 10-YR MARGIN HISTORY + PEER BENCHMARKS — Bloomberg
B23: £m / % | C23: FY17 | D23: FY18 | E23: FY19 | F23: FY20 | G23: FY21 | H23: FY22 | I23: FY23 | J23: FY24 | K23: FY25
B24: Revenue (£m) | C24: 15.42 | D24: 16.47 | E24: 18.21 | F24: 17.33 | G24: 19.86 | H24: 26.1 | I24: 27.93 | J24: 31.49 | K24: 35.23
B25: EBITDA (£m) | C25: 0.15 | D25: 0.39 | E25: 0.75 | F25: 0.68 | G25: 1.33 | H25: 1.21 | I25: 0.86 | J25: 1.17 | K25: 1.13
B26: EBITDA margin | C26: 0.0095 | D26: 0.0234 | E26: 0.0412 | F26: 0.0395 | G26: 0.0669 | H26: 0.0463 | I26: 0.0309 | J26: 0.0371 | K26: 0.0322
B27: Source: Bloomberg 9136763Z LN Equity, FY17-FY25. 10-yr avg margin ~3.4%; 5-yr avg (FY21-25) 4.27%; FY21 peak 6.69%.
B32: ENTRY ANCHORS — Companies House FY March 2025 (£m unless stated)
B33: FY25 Revenue (£m) | C33: 35.017 | E33: VERIFIED | F33: CH Tyre Spot Ltd FY25 p.12 — Statement of Income & Retained Earnings
B34: FY25 Cost of sales (£m) | C34: -26.009 | E34: VERIFIED | F34: CH FY25 p.12
B35: FY25 Gross profit (£m) | C35: =C33+C34 -> 9.008 | E35: CALCULABLE | F35: Revenue − COGS
B36: FY25 Operating profit (£m) | C36: 0.753 | E36: VERIFIED | F36: CH FY25 p.12
B37: FY25 Depreciation (£m) | C37: 0.368 | E37: VERIFIED | F37: CH FY25 Note 4 (p.20)
B38: FY25 Amortisation (£m) | C38: 0.005 | E38: VERIFIED | F38: CH FY25 Note 4 (p.20)
B39: FY25 EBITDA (£m) | C39: =C36+C37+C38 -> 1.126 | E39: CALCULABLE | F39: Op profit + D&A — reconciles to £1.13m
B40: FY25 EBITDA margin | C40: =C39/C33 -> 0.03215581 | E40: CALCULABLE | F40: Derived ≈3.2%
B42: Bank loans (£m) | C42: 0.415 | E42: VERIFIED | F42: CH FY25 Note 19 (p.25)
B43: Bank overdrafts (£m) | C43: 0.807 | E43: VERIFIED | F43: CH FY25 Note 19 (p.25)
B44: Cash (£m) | C44: 0.03 | E44: VERIFIED | F44: CH FY25 Balance Sheet (p.13)
B45: Net debt at entry (£m) | C45: =C42+C43-C44 -> 1.192 | E45: CALCULABLE | F45: Bank loans + overdraft − cash = £1.19m
B46: Tangible fixed assets (£m) | C46: 4.516 | E46: VERIFIED | F46: CH FY25 BS — of which £2.79m freehold pledged as security (Note 12, p.23)
B47: Stocks (£m) | C47: 4.909 | E47: VERIFIED | F47: CH FY25 BS — funds wholesale book; 69 days COGS
B48: Trade debtors (£m) | C48: 3.614 | E48: VERIFIED | F48: CH FY25 Note 16
B49: Retained earnings c/f (£m) | C49: 6.621 | E49: VERIFIED | F49: CH FY25 BS
B51: TRANSACTION ASSUMPTIONS — ALL ILLUSTRATIVE, NOT DEAL INDICATIONS
B52: Entry EV / EBITDA multiple (x) | C52: 5.75 | E52: ASSUMPTION | F52: Anchored to Halfords Group spot 5.4x (BBG HFD LN, 23-May-26). 5.75x = 7% premium for off-market private + Kerr's adjacency. Through-cycle Halfords likely 6-7x.
B53: Implied Entry Enterprise Value (£m) | C53: =C39*C52 -> 6.4745 | E53: CALCULABLE | F53: EBITDA × entry multiple
B54: New senior debt at entry (£m) | C54: 3.5 | E54: ASSUMPTION | F54: Refinances existing £1.22m + funds £2.28m of consideration. ~3.1x EBITDA — moderate for turnaround profile.
B55: Take out existing senior debt (£m) | C55: =C42+C43 -> 1.222 | E55: CALCULABLE | F55: Existing bank loans + overdraft (refinanced at close)
B56: Management rollover (£m) | C56: 0.2 | E56: ASSUMPTION | F56: Next-gen director Mr J T Shaw (b. 1978) retains stake
B57: Transaction fees (£m) | C57: 0.29 | E57: ASSUMPTION | F57: ~4.5% of EV — legal + financial DD + advisory for sub-£10m bolt-on
B58: Working capital injection (£m) | C58: 0.4 | E58: ASSUMPTION | F58: Rebuild cash buffer (FY25 ended £30k)
B59: Entry leverage (x EBITDA) | C59: =C54/C39 -> 3.1083481 | E59: CALCULABLE | F59: New senior debt / entry EBITDA
B61: OPERATING ASSUMPTIONS — projection inputs
B62: Revenue growth p.a. (%) | C62: 0.08 | D62: 0.06 | E62: 0.04 | F62: 0.03 | G62: ASSUMPTION | H62: Tapers from FY25 +12.3% actual to UK tyre market CAGR ~4%
B63: EBITDA margin trajectory (%) | C63: 0.04 | D63: 0.042 | E63: 0.044 | F63: 0.046 | G63: ASSUMPTION | H63: CONSERVATIVE base: Y4 4.6% = return to FY22 actual (already achieved). Bull case (sensitivity) = 7% margin between TS FY21 peak 6.69% and Halfords AC 9.58% peer ceiling.
B64: D&A % of revenue | C64: =(C37+C38)/C33 -> 0.010651969 | E64: CALCULABLE | F64: FY25 D&A / FY25 revenue ≈ 1.07%
B65: Capex % of revenue (%) | C65: 0.02 | E65: ASSUMPTION | F65: CONSERVATIVE: FY24 actual capex £770k = 2.5%; FY25 actual £242k = 0.7%; 2.0% normalised midpoint
B66: NWC change % of revenue change | C66: 0.219 | E66: CALCULABLE | F66: 2-yr avg from Note 27: (FY24 ΔWC £1,554k + FY25 ΔWC -£111k) / (ΔRev FY24 £2,748k + ΔRev FY25 £3,841k) = 21.9%
B67: Cash tax rate (%) | C67: 0.25 | E67: ASSUMPTION | F67: UK corporation tax main rate
B68: Senior debt interest rate (%) | C68: 0.085 | E68: ASSUMPTION | F68: SONIA + 400-500bps for UK LMM senior; not based on debt market sounding
B69: Cash sweep (% of FCF) | C69: 0.75 | E69: ASSUMPTION | F69: 75% sweep above minimum cash — typical PE LBO covenant
B70: Minimum cash (£m) | C70: 0.5 | E70: ASSUMPTION | F70: Operating cash floor
B72: EXIT ASSUMPTIONS
B73: Hold period (years) | C73: 4 | E73: ASSUMPTION | F73: Aligns with Kerr's platform exit window
B74: Exit EV / EBITDA multiple (x) | C74: 6 | E74: ASSUMPTION | F74: CONSERVATIVE: Halfords spot 5.4x (BBG VERIFIED). 6.0x = modest 11% premium for platform scale at exit (~60 sites). 7.0x reserved for bull case.
B76: ENTRY NET DEBT WALK — Phase 2 verified
B77: Bank loans (refinance at close) | C77: 0.415 | E77: VERIFIED | F77: FY25 Note 19 (p.25)
B78: Bank overdrafts (refinance at close) | C78: 0.807 | E78: VERIFIED | F78: FY25 Note 19 (p.25)
B79: + Director loans outstanding | C79: 0.027 | E79: VERIFIED | F79: FY25 Note 25 (p.27)
B80: - Cash at bank | C80: -0.03 | E80: VERIFIED | F80: FY25 BS (p.13)
B81: Total entry net debt (£m) | C81: =SUM(C77:C80) -> 1.219 | E81: CALCULABLE | F81: Refinanced at close via new senior facility
B100: PEER BENCHMARKS — Halfords Autocentres + Kerr's (Bloomberg)
B101: Comp | C101: FY25 Rev (£m) | D101: FY25 EBITDA (£m) | E101: EBITDA margin | F101: Source
B102: Tyre Spot (current) | C102: 35.02 | D102: 1.13 | E102: 0.0322 | F102: [VERIFIED] CH FY25 + BBG 9136763Z LN
B103: Tyre Spot FY21 peak | C103: 19.86 | D103: 1.33 | E103: 0.0669 | F103: [VERIFIED] BBG 9136763Z LN — own historical peak
B104: Kerr's Tyres FY25 (Sep YE, pre-Farmer) | C104: 17.3 | D104: 1.64 | E104: 0.0951 | F104: [VERIFIED] BBG 1954169D LN — direct peer, same buyer
B105: Halfords Autocentres FY25 | C105: 710.3 | D105: 62 | E105: 0.0873 | F105: [VERIFIED] BBG HFD LN Segment Data — scale benchmark
B106: Halfords Autocentres 5-yr avg | E106: 0.0958 | F106: [CALCULABLE] avg FY21-25 from BBG HFD LN
B107: Halfords Group EV/EBITDA (current) | E107: 5.4x | F107: [VERIFIED] BBG HFD LN — spot 23-May-2026; through-cycle likely 6-7x
B109: IMPLICATIONS for Tyre Spot:
B110: • Tyre Spot already hit 6.69% margin in FY21 — recovery to 4-6% is a return to recent history
B111: • Halfords Autocentres averages 9.58% over 5 yrs; Kerr's currently runs 9.51% — operating ceiling is verified
B112: • Each 100bps of margin recovery on £35m revenue = £350k EBITDA
B113: • Entry multiple anchored to Halfords spot 5.4x — model uses 5.75x as modest premium for off-market private discount

Sheet Model
B1: TYRE SPOT — LBO MODEL
B3: INPUTS — key drivers (links to Cover & Assumptions sheet)
B5: Purchase Assumptions | F5: Financing Assumptions
B6: Purchase EBITDA (£m) | C6: ='Cover & Assumptions'!C39 -> 1.126 | F6: % LTC (senior debt / EV) | G6: ='Cover & Assumptions'!C54/'Cover & Assumptions'!C53 -> 0.54058228 | H6: Interest Rate | I6: ='Cover & Assumptions'!C68 -> 0.085
B7: Purchase Multiple (x) | C7: ='Cover & Assumptions'!C52 -> 5.75 | F7: Aggregate Financing (£m) | G7: ='Cover & Assumptions'!C54 -> 3.5
B8: Purchase EV (£m) | C8: =C6*C7 -> 6.4745
B9: Plus: Cash (£m) | C9: ='Cover & Assumptions'!C44 -> 0.03
B10: Less: Existing Debt (£m) | C10: =-('Cover & Assumptions'!C42+'Cover & Assumptions'!C43+'Cover & Assumptions'!C79) -> -1.249
B11: Purchase Equity Value (£m) | C11: =C8+C9+C10 -> 5.2555
B13: P&L Assumptions | F13: Exit Assumptions
B14: Revenue Growth (4-yr avg) | C14: =AVERAGE('Cover & Assumptions'!C62:F62) -> 0.0525 | F14: Exit Multiple (x LTM EBITDA) | G14: ='Cover & Assumptions'!C74 -> 6
B15: Y4 EBITDA Margin Target | C15: ='Cover & Assumptions'!F63 -> 0.046 | F15: Hold Period (years) | G15: ='Cover & Assumptions'!C73 -> 4
B16: Tax Rate | C16: ='Cover & Assumptions'!C67 -> 0.25
B18: Uses of Capital (£m) | F18: Sources of Capital (£m)
B19: Purchase Company's Equity | C19: =C11 -> 5.2555 | F19: % LTC | G19: £m
B20: Retire Existing Debt | C20: =-C10 -> 1.249 | F20: Aggregate Financing | G20: =G6 -> 0.54058228 | H20: =G7 -> 3.5
B21: Working Capital Injection | C21: ='Cover & Assumptions'!C58 -> 0.4 | F21: Management Rollover | G21: =H21/C24 -> 0.027799013 | H21: ='Cover & Assumptions'!C56 -> 0.2
B22: Transaction Expenses | C22: ='Cover & Assumptions'!C57 -> 0.29 | F22: Sponsor Equity (plug) | G22: =1-G20-G21 -> 0.4316187 | H22: =C24-H20-H21 -> 3.4945
B23: Total Uses | C23: =SUM(C19:C22) -> 7.1945 | F23: Total Sources | G23: =SUM(G20:G22) -> 1 | H23: =SUM(H20:H22) -> 7.1945
B24: Sources = Uses? | C24: =C23 -> 7.1945 | F24: Ties? | G24: =IF(ROUND(H23-C23,2)=0,"OK","ERROR") -> OK
B26: Detailed Operating Model + Debt Schedule + Returns + Sensitivity below
B30: Revenue | C30: ='Cover & Assumptions'!$C$33 -> 35.017 | D30: =C30*(1+'Cover & Assumptions'!C62) -> 37.81836 | E30: =D30*(1+'Cover & Assumptions'!D62) -> 40.087462 | F30: =E30*(1+'Cover & Assumptions'!E62) -> 41.69096 | G30: =F30*(1+'Cover & Assumptions'!F62) -> 42.941689
B31: EBITDA margin | C31: ='Cover & Assumptions'!$C$40 -> 0.03215581 | D31: ='Cover & Assumptions'!C63 -> 0.04 | E31: ='Cover & Assumptions'!D63 -> 0.042 | F31: ='Cover & Assumptions'!E63 -> 0.044 | G31: ='Cover & Assumptions'!F63 -> 0.046
B32: EBITDA | C32: =C30*C31 -> 1.126 | D32: =D30*D31 -> 1.5127344 | E32: =E30*E31 -> 1.6836734 | F32: =F30*F31 -> 1.8344022 | G32: =G30*G31 -> 1.9753177
B33: Depreciation & amortisation | C33: =-C30*'Cover & Assumptions'!$C$64 -> -0.373 | D33: =-D30*'Cover & Assumptions'!$C$64 -> -0.40284 | E33: =-E30*'Cover & Assumptions'!$C$64 -> -0.4270104 | F33: =-F30*'Cover & Assumptions'!$C$64 -> -0.44409082 | G33: =-G30*'Cover & Assumptions'!$C$64 -> -0.45741354
B34: EBIT | C34: =C32+C33 -> 0.753 | D34: =D32+D33 -> 1.1098944 | E34: =E32+E33 -> 1.256663 | F34: =F32+F33 -> 1.3903114 | G34: =G32+G33 -> 1.5179041
B35: Cash interest (senior) | C35: 0 | D35: =-D54 -> -0.2975 | E35: =-E54 -> -0.26775 | F35: =-F54 -> -0.238 | G35: =-G54 -> -0.20825
B36: Profit before tax | C36: =C34+C35 -> 0.753 | D36: =D34+D35 -> 0.8123944 | E36: =E34+E35 -> 0.98891299 | F36: =F34+F35 -> 1.1523114 | G36: =G34+G35 -> 1.3096541
B37: Cash tax | C37: =-MAX(0,C36)*'Cover & Assumptions'!$C$67 -> -0.18825 | D37: =-MAX(0,D36)*'Cover & Assumptions'!$C$67 -> -0.2030986 | E37: =-MAX(0,E36)*'Cover & Assumptions'!$C$67 -> -0.24722825 | F37: =-MAX(0,F36)*'Cover & Assumptions'!$C$67 -> -0.28807786 | G37: =-MAX(0,G36)*'Cover & Assumptions'!$C$67 -> -0.32741354
B38: Net profit | C38: =C36+C37 -> 0.56475 | D38: =D36+D37 -> 0.6092958 | E38: =E36+E37 -> 0.74168474 | F38: =F36+F37 -> 0.86423357 | G38: =G36+G37 -> 0.98224061
B40: FREE CASH FLOW BUILD
B41: EBITDA | C41: =C32 -> 1.126 | D41: =D32 -> 1.5127344 | E41: =E32 -> 1.6836734 | F41: =F32 -> 1.8344022 | G41: =G32 -> 1.9753177
B42: Less: capex | C42: =-C30*'Cover & Assumptions'!$C$65 -> -0.70034 | D42: =-D30*'Cover & Assumptions'!$C$65 -> -0.7563672 | E42: =-E30*'Cover & Assumptions'!$C$65 -> -0.80174923 | F42: =-F30*'Cover & Assumptions'!$C$65 -> -0.8338192 | G42: =-G30*'Cover & Assumptions'!$C$65 -> -0.85883378
B43: Less: change in working capital | C43: 0 | D43: =-(D30-C30)*'Cover & Assumptions'!$C$66 -> -0.61349784 | E43: =-(E30-D30)*'Cover & Assumptions'!$C$66 -> -0.49693325 | F43: =-(F30-E30)*'Cover & Assumptions'!$C$66 -> -0.35116616 | G43: =-(G30-F30)*'Cover & Assumptions'!$C$66 -> -0.27390961
B44: Less: cash interest | C44: =C35 -> 0 | D44: =D35 -> -0.2975 | E44: =E35 -> -0.26775 | F44: =F35 -> -0.238 | G44: =G35 -> -0.20825
B45: Less: cash tax | C45: =C37 -> -0.18825 | D45: =D37 -> -0.2030986 | E45: =E37 -> -0.24722825 | F45: =F37 -> -0.28807786 | G45: =G37 -> -0.32741354
B46: Free cash flow (pre-debt repayment) | C46: =SUM(C41:C45) -> 0.23741 | D46: =SUM(D41:D45) -> -0.35772924 | E46: =SUM(E41:E45) -> -0.12998734 | F46: =SUM(F41:F45) -> 0.12333902 | G46: =SUM(G41:G45) -> 0.30691077
B48: ACQUISITION DEBT SCHEDULE & CASH SWEEP
B49: £m | C49: FY25A (Entry) | D49: Year 1 | E49: Year 2 | F49: Year 3 | G49: Year 4
B50: Opening Acquisition debt | C50: ='Cover & Assumptions'!$C$54 -> 3.5 | D50: =C50 -> 3.5 | E50: =D55 -> 3.15 | F50: =E55 -> 2.8 | G50: =F55 -> 2.45
B51: Interest rate | C51: ='Cover & Assumptions'!$C$68 -> 0.085 | D51: ='Cover & Assumptions'!$C$68 -> 0.085 | E51: ='Cover & Assumptions'!$C$68 -> 0.085 | F51: ='Cover & Assumptions'!$C$68 -> 0.085 | G51: ='Cover & Assumptions'!$C$68 -> 0.085
B52: Mandatory amortisation | C52: 0 | D52: =MIN(D50, 'Cover & Assumptions'!$C$54*0.1) -> 0.35 | E52: =MIN(E50, 'Cover & Assumptions'!$C$54*0.1) -> 0.35 | F52: =MIN(F50, 'Cover & Assumptions'!$C$54*0.1) -> 0.35 | G52: =MIN(G50, 'Cover & Assumptions'!$C$54*0.1) -> 0.35
B53: Cash sweep (% of FCF available) | C53: 0 | D53: =MIN(MAX(0,D50-D52),MAX(0,D46-D52)*'Cover & Assumptions'!$C$69) -> 0 | E53: =MIN(MAX(0,E50-E52),MAX(0,E46-E52)*'Cover & Assumptions'!$C$69) -> 0 | F53: =MIN(MAX(0,F50-F52),MAX(0,F46-F52)*'Cover & Assumptions'!$C$69) -> 0 | G53: =MIN(MAX(0,G50-G52),MAX(0,G46-G52)*'Cover & Assumptions'!$C$69) -> 0
B54: Cash interest | C54: 0 | D54: =D50*D51 -> 0.2975 | E54: =E50*E51 -> 0.26775 | F54: =F50*F51 -> 0.238 | G54: =G50*G51 -> 0.20825
B55: Closing senior debt | C55: =C50 -> 3.5 | D55: =MAX(0,D50-D52-D53) -> 3.15 | E55: =MAX(0,E50-E52-E53) -> 2.8 | F55: =MAX(0,F50-F52-F53) -> 2.45 | G55: =MAX(0,G50-G52-G53) -> 2.1
B57: Note: Interest computed on opening balance (avoids circular with sweep). Sweep takes 75% of FCF after mandatory amort.
B59: RETURNS — equity bridge
B60: EXIT (Year 4) — ILLUSTRATIVE
B61: Year 4 EBITDA | C61: =G32 -> 1.9753177
B62: Exit EV / EBITDA multiple | C62: ='Cover & Assumptions'!$C$74 -> 6
B63: Exit Enterprise Value | C63: =C61*C62 -> 11.851906
B64: Less: net senior debt at exit | C64: =-(G55-'Cover & Assumptions'!$C$70) -> -1.6
B65: Exit equity value | C65: =C63+C64 -> 10.251906
B67: RETURNS TO SPONSOR
B68: Sponsor equity invested at entry | C68: =H22 -> 3.4945
B69: Sponsor equity at exit (assume pro-rata) | C69: =C65*(C68/(C68+H21)) -> 9.6969241
B70: MOIC | C70: =C69/C68 -> 2.7749103
B71: Hold period (years) | C71: ='Cover & Assumptions'!$C$73 -> 4
B72: IRR (single in / single out) | C72: =(C70)^(1/C71)-1 -> 0.29066115
B74: CASH-FLOW CROSS-CHECK
B75: Year | C75: 0 | D75: 1 | E75: 2 | F75: 3 | G75: 4
B76: Sponsor cash flow (£m) | C76: =-C68 -> -3.4945 | D76: 0 | E76: 0 | F76: 0 | G76: =C69 -> 9.6969241
B77: IRR (Excel, on cash flows) | C77: =IRR(C76:G76) -> 0.29066115 | D77: Cross-check against closed-form IRR — should match
B79: SENSITIVITY — illustrative
B80: Two biggest swing factors: Year-4 EBITDA (margin discipline) × Exit multiple.
B82: Entry sponsor equity (£m) | C82: =H22 -> 3.4945
B83: Year 4 net debt at exit (£m) | C83: =G55 -> 2.1
B85: TABLE 1 — MOIC: Y4 EBITDA × Exit multiple
B86: Y4 EBITDA \ Exit x | C86: 5 | D86: 6 | E86: 7 | F86: 8 | G86: 9
B87: 1.1 | C87: =MAX(0,(($B87*C$86-$C$83)*$C$82/(($C$82+'Cover & Assumptions'!$C$56))))/($C$82) -> 0.92028691 | D87: =MAX(0,(($B87*D$86-$C$83)*$C$82/(($C$82+'Cover & Assumptions'!$C$56))))/($C$82) -> 1.2180268 | E87: =MAX(0,(($B87*E$86-$C$83)*$C$82/(($C$82+'Cover & Assumptions'!$C$56))))/($C$82) -> 1.5157667 | F87: =MAX(0,(($B87*F$86-$C$83)*$C$82/(($C$82+'Cover & Assumptions'!$C$56))))/($C$82) -> 1.8135066 | G87: =MAX(0,(($B87*G$86-$C$83)*$C$82/(($C$82+'Cover & Assumptions'!$C$56))))/($C$82) -> 2.1112464
B88: 1.5 | C88: =MAX(0,(($B88*C$86-$C$83)*$C$82/(($C$82+'Cover & Assumptions'!$C$56))))/($C$82) -> 1.4616322 | D88: =MAX(0,(($B88*D$86-$C$83)*$C$82/(($C$82+'Cover & Assumptions'!$C$56))))/($C$82) -> 1.8676411 | E88: =MAX(0,(($B88*E$86-$C$83)*$C$82/(($C$82+'Cover & Assumptions'!$C$56))))/($C$82) -> 2.27365 | F88: =MAX(0,(($B88*F$86-$C$83)*$C$82/(($C$82+'Cover & Assumptions'!$C$56))))/($C$82) -> 2.679659 | G88: =MAX(0,(($B88*G$86-$C$83)*$C$82/(($C$82+'Cover & Assumptions'!$C$56))))/($C$82) -> 3.0856679
B89: 1.8 | C89: =MAX(0,(($B89*C$86-$C$83)*$C$82/(($C$82+'Cover & Assumptions'!$C$56))))/($C$82) -> 1.8676411 | D89: =MAX(0,(($B89*D$86-$C$83)*$C$82/(($C$82+'Cover & Assumptions'!$C$56))))/($C$82) -> 2.3548518 | E89: =MAX(0,(($B89*E$86-$C$83)*$C$82/(($C$82+'Cover & Assumptions'!$C$56))))/($C$82) -> 2.8420625 | F89: =MAX(0,(($B89*F$86-$C$83)*$C$82/(($C$82+'Cover & Assumptions'!$C$56))))/($C$82) -> 3.3292732 | G89: =MAX(0,(($B89*G$86-$C$83)*$C$82/(($C$82+'Cover & Assumptions'!$C$56))))/($C$82) -> 3.816484
B90: 2 | C90: =MAX(0,(($B90*C$86-$C$83)*$C$82/(($C$82+'Cover & Assumptions'!$C$56))))/($C$82) -> 2.1383137 | D90: =MAX(0,(($B90*D$86-$C$83)*$C$82/(($C$82+'Cover & Assumptions'!$C$56))))/($C$82) -> 2.679659 | E90: =MAX(0,(($B90*E$86-$C$83)*$C$82/(($C$82+'Cover & Assumptions'!$C$56))))/($C$82) -> 3.2210042 | F90: =MAX(0,(($B90*F$86-$C$83)*$C$82/(($C$82+'Cover & Assumptions'!$C$56))))/($C$82) -> 3.7623494 | G90: =MAX(0,(($B90*G$86-$C$83)*$C$82/(($C$82+'Cover & Assumptions'!$C$56))))/($C$82) -> 4.3036947
B91: 2.5 | C91: =MAX(0,(($B91*C$86-$C$83)*$C$82/(($C$82+'Cover & Assumptions'!$C$56))))/($C$82) -> 2.8149953 | D91: =MAX(0,(($B91*D$86-$C$83)*$C$82/(($C$82+'Cover & Assumptions'!$C$56))))/($C$82) -> 3.4916768 | E91: =MAX(0,(($B91*E$86-$C$83)*$C$82/(($C$82+'Cover & Assumptions'!$C$56))))/($C$82) -> 4.1683584 | F91: =MAX(0,(($B91*F$86-$C$83)*$C$82/(($C$82+'Cover & Assumptions'!$C$56))))/($C$82) -> 4.8450399 | G91: =MAX(0,(($B91*G$86-$C$83)*$C$82/(($C$82+'Cover & Assumptions'!$C$56))))/($C$82) -> 5.5217215
B92: 3 | C92: =MAX(0,(($B92*C$86-$C$83)*$C$82/(($C$82+'Cover & Assumptions'!$C$56))))/($C$82) -> 3.4916768 | D92: =MAX(0,(($B92*D$86-$C$83)*$C$82/(($C$82+'Cover & Assumptions'!$C$56))))/($C$82) -> 4.3036947 | E92: =MAX(0,(($B92*E$86-$C$83)*$C$82/(($C$82+'Cover & Assumptions'!$C$56))))/($C$82) -> 5.1157125 | F92: =MAX(0,(($B92*F$86-$C$83)*$C$82/(($C$82+'Cover & Assumptions'!$C$56))))/($C$82) -> 5.9277304 | G92: =MAX(0,(($B92*G$86-$C$83)*$C$82/(($C$82+'Cover & Assumptions'!$C$56))))/($C$82) -> 6.7397483
B95: TABLE 2 — IRR (4-year hold): Y4 EBITDA × Exit multiple
B96: Y4 EBITDA \ Exit x | C96: 5 | D96: 6 | E96: 7 | F96: 8 | G96: 9
B97: 1.1 | C97: =IFERROR((C87)^(1/'Cover & Assumptions'!$C$73)-1,0) -> -0.020553291 | D97: =IFERROR((D87)^(1/'Cover & Assumptions'!$C$73)-1,0) -> 0.050543913 | E97: =IFERROR((E87)^(1/'Cover & Assumptions'!$C$73)-1,0) -> 0.10957864 | F97: =IFERROR((F87)^(1/'Cover & Assumptions'!$C$73)-1,0) -> 0.16045895 | G97: =IFERROR((G87)^(1/'Cover & Assumptions'!$C$73)-1,0) -> 0.20540984
B98: 1.5 | C98: =IFERROR((C88)^(1/'Cover & Assumptions'!$C$73)-1,0) -> 0.099536175 | D98: =IFERROR((D88)^(1/'Cover & Assumptions'!$C$73)-1,0) -> 0.16902381 | E98: =IFERROR((E88)^(1/'Cover & Assumptions'!$C$73)-1,0) -> 0.22795062 | F98: =IFERROR((F88)^(1/'Cover & Assumptions'!$C$73)-1,0) -> 0.27943987 | G98: =IFERROR((G88)^(1/'Cover & Assumptions'!$C$73)-1,0) -> 0.32537049
B99: 1.8 | C99: =IFERROR((C89)^(1/'Cover & Assumptions'!$C$73)-1,0) -> 0.16902381 | D99: =IFERROR((D89)^(1/'Cover & Assumptions'!$C$73)-1,0) -> 0.23877062 | E99: =IFERROR((E89)^(1/'Cover & Assumptions'!$C$73)-1,0) -> 0.2983997 | F99: =IFERROR((F89)^(1/'Cover & Assumptions'!$C$73)-1,0) -> 0.35078852 | G99: =IFERROR((G89)^(1/'Cover & Assumptions'!$C$73)-1,0) -> 0.3977061
B100: 2 | C100: =IFERROR((C90)^(1/'Cover & Assumptions'!$C$73)-1,0) -> 0.2092549 | D100: =IFERROR((D90)^(1/'Cover & Assumptions'!$C$73)-1,0) -> 0.27943987 | E100: =IFERROR((E90)^(1/'Cover & Assumptions'!$C$73)-1,0) -> 0.33966997 | F100: =IFERROR((F90)^(1/'Cover & Assumptions'!$C$73)-1,0) -> 0.39272311 | G100: =IFERROR((G90)^(1/'Cover & Assumptions'!$C$73)-1,0) -> 0.44032455
B101: 2.5 | C101: =IFERROR((C91)^(1/'Cover & Assumptions'!$C$73)-1,0) -> 0.29529717 | D101: =IFERROR((D91)^(1/'Cover & Assumptions'!$C$73)-1,0) -> 0.36696851 | E101: =IFERROR((E91)^(1/'Cover & Assumptions'!$C$73)-1,0) -> 0.42886521 | F101: =IFERROR((F91)^(1/'Cover & Assumptions'!$C$73)-1,0) -> 0.48362567 | G101: =IFERROR((G91)^(1/'Cover & Assumptions'!$C$73)-1,0) -> 0.53291694
B102: 3 | C102: =IFERROR((C92)^(1/'Cover & Assumptions'!$C$73)-1,0) -> 0.36696851 | D102: =IFERROR((D92)^(1/'Cover & Assumptions'!$C$73)-1,0) -> 0.44032455 | E102: =IFERROR((E92)^(1/'Cover & Assumptions'!$C$73)-1,0) -> 0.50392623 | F102: =IFERROR((F92)^(1/'Cover & Assumptions'!$C$73)-1,0) -> 0.56035031 | G102: =IFERROR((G92)^(1/'Cover & Assumptions'!$C$73)-1,0) -> 0.61124254
B104: Note: Table 2 IRR derives from Table 1 MOIC (single in/single out). Year-4 net debt held constant — at higher EBITDA scenarios the debt would deleverage further (returns above are if anything conservative).
